keybindings/__init__.py
keybindings/device_listener.py
panda3d_keybindings-0.3a1.dist-info/LICENSE
panda3d_keybindings-0.3a1.dist-info/METADATA
panda3d_keybindings-0.3a1.dist-info/WHEEL
panda3d_keybindings-0.3a1.dist-info/top_level.txt
panda3d_keybindings-0.3a1.dist-info/RECORD
