Metadata-Version: 2.1
Name: panda3d-keybindings
Version: 0.3a1
Summary: A more abstract interface for using input devices in Panda3D.
Home-page: https://github.com/TheCheapestPixels/panda3d-keybindings
Author: TheCheapestPixels
Author-email: TheCheapestPixels@gmail.com
License: UNKNOWN
Keywords: panda3d keybinding keybindings keymapping
Platform: UNKNOWN
Classifier: Development Status :: 4 - Beta
Classifier: Intended Audience :: Developers
Classifier: License :: OSI Approved :: BSD License
Classifier: Programming Language :: Python :: 3.5
Classifier: Programming Language :: Python :: 3.6
Classifier: Programming Language :: Python :: 3.7
Classifier: Programming Language :: Python :: 3.8
Classifier: Programming Language :: Python :: 3.9
Requires-Python: >=3.5
Requires-Dist: panda3d
